camelot/__init__.py
camelot/__main__.py
camelot/__version__.py
camelot/backends/__init__.py
camelot/backends/ghostscript_backend.py
camelot/backends/image_conversion.py
camelot/backends/poppler_backend.py
camelot/cli.py
camelot/core.py
camelot/handlers.py
camelot/image_processing.py
camelot/io.py
camelot/parsers/__init__.py
camelot/parsers/base.py
camelot/parsers/lattice.py
camelot/parsers/stream.py
camelot/plotting.py
camelot/py.typed
camelot/utils.py
camelot_fork-0.20.1.dist-info/METADATA
camelot_fork-0.20.1.dist-info/entry_points.txt
camelot_fork-0.20.1.dist-info/WHEEL
camelot_fork-0.20.1.dist-info/LICENSE
camelot_fork-0.20.1.dist-info/RECORD
