Metadata-Version: 2.1
Name: camelot-fork
Version: 0.20.1
Summary: Camelot Fork
Home-page: https://github.com/foarsitter/camelot-fork
License: MIT
Author: Jelmer Draaijer
Author-email: info@jelmert.nl
Requires-Python: >=3.8,<4.0
Classifier: Development Status :: 5 - Production/Stable
Classifier: License :: OSI Approved :: MIT License
Classifier: Programming Language :: Python :: 3
Classifier: Programming Language :: Python :: 3.8
Classifier: Programming Language :: Python :: 3.9
Classifier: Programming Language :: Python :: 3.10
Classifier: Programming Language :: Python :: 3.11
Requires-Dist: chardet (>=5.1.0,<6.0.0)
Requires-Dist: click (>=8.0.1)
Requires-Dist: numpy (>=1.24.2,<2.0.0)
Requires-Dist: openpyxl (>=3.1.0,<4.0.0)
Requires-Dist: pandas (>=1.5.3,<2.0.0)
Requires-Dist: pdfminer-six (>=20221105,<20221106)
Requires-Dist: pypdf (>=3.4.0,<4.0.0)
Requires-Dist: tabulate (>=0.9.0,<0.10.0)
Project-URL: Changelog, https://github.com/foarsitter/camelot-fork/releases
Project-URL: Documentation, https://camelot-fork.readthedocs.io
Project-URL: Repository, https://github.com/foarsitter/camelot-fork
